{
    "openapi": "3.1.0",
    "info": {
        "title": "modularize-rbac/laravel admin API",
        "description": "REST API for the modularize-rbac/laravel admin panel. Every response carries an `Access-Api-Version` header.",
        "version": "1.0.0"
    },
    "servers": [
        {
            "url": "/api/admin",
            "description": "Default route prefix"
        }
    ],
    "paths": {
        "/modules": {
            "get": {
                "tags": [
                    "modules"
                ],
                "operationId": "modules.index",
                "parameters": [
                    {
                        "name": "limit",
                        "in": "query",
                        "schema": {
                            "type": "integer",
                            "maximum": 1000,
                            "minimum": 1
                        }
                    },
                    {
                        "name": "offset",
                        "in": "query",
                        "schema": {
                            "type": "integer",
                            "minimum": 0
                        }
                    },
                    {
                        "name": "is_active",
                        "in": "query",
                        "schema": {
                            "type": "boolean"
                        }
                    },
                    {
                        "name": "root_module_id",
                        "in": "query",
                        "schema": {
                            "type": "string",
                            "format": "uuid"
                        }
                    },
                    {
                        "name": "slug_like",
                        "in": "query",
                        "schema": {
                            "type": "string"
                        }
                    }
                ],
                "responses": {
                    "200": {
                        "description": "OK",
                        "content": {
                            "application/json": {
                                "schema": {
                                    "properties": {
                                        "data": {
                                            "type": "array",
                                            "items": {
                                                "$ref": "#/components/schemas/Module"
                                            }
                                        },
                                        "meta": {
                                            "oneOf": [
                                                {
                                                    "$ref": "#/components/schemas/PaginatedMeta"
                                                },
                                                {
                                                    "properties": {
                                                        "count": {
                                                            "type": "integer"
                                                        }
                                                    },
                                                    "type": "object"
                                                }
                                            ]
                                        }
                                    },
                                    "type": "object"
                                }
                            }
                        }
                    },
                    "422": {
                        "description": "Invalid query parameter",
                        "content": {
                            "application/json": {
                                "schema": {
                                    "$ref": "#/components/schemas/Error"
                                }
                            }
                        }
                    }
                }
            },
            "post": {
                "tags": [
                    "modules"
                ],
                "operationId": "modules.store",
                "requestBody": {
                    "required": true,
                    "content": {
                        "application/json": {
                            "schema": {
                                "properties": {
                                    "slug": {
                                        "type": "string"
                                    },
                                    "name": {
                                        "type": "string"
                                    },
                                    "redirect": {
                                        "type": [
                                            "string",
                                            "null"
                                        ]
                                    },
                                    "icon": {
                                        "type": [
                                            "string",
                                            "null"
                                        ]
                                    },
                                    "root_module_id": {
                                        "type": [
                                            "string",
                                            "null"
                                        ],
                                        "format": "uuid"
                                    },
                                    "sort_order": {
                                        "type": "integer"
                                    },
                                    "is_active": {
                                        "type": "boolean"
                                    },
                                    "translations": {
                                        "type": "object"
                                    }
                                },
                                "type": "object"
                            }
                        }
                    }
                },
                "responses": {
                    "201": {
                        "description": "Created",
                        "content": {
                            "application/json": {
                                "schema": {
                                    "properties": {
                                        "data": {
                                            "$ref": "#/components/schemas/Module"
                                        }
                                    },
                                    "type": "object"
                                }
                            }
                        }
                    },
                    "422": {
                        "description": "Validation failed"
                    }
                }
            }
        },
        "/modules/bulk": {
            "post": {
                "tags": [
                    "modules"
                ],
                "description": "Subject to the `access-bulk` rate limiter (default 10/min/user).",
                "operationId": "modules.bulkStore",
                "requestBody": {
                    "required": true,
                    "content": {
                        "application/json": {
                            "schema": {
                                "properties": {
                                    "modules": {
                                        "type": "array",
                                        "items": {
                                            "type": "object"
                                        }
                                    }
                                },
                                "type": "object"
                            }
                        }
                    }
                },
                "responses": {
                    "201": {
                        "description": "Created"
                    },
                    "422": {
                        "description": "Validation failed"
                    },
                    "429": {
                        "description": "Rate limited"
                    }
                }
            },
            "delete": {
                "tags": [
                    "modules"
                ],
                "description": "Subject to the `access-bulk` rate limiter.",
                "operationId": "modules.bulkDestroy",
                "requestBody": {
                    "required": true,
                    "content": {
                        "application/json": {
                            "schema": {
                                "properties": {
                                    "ids": {
                                        "type": "array",
                                        "items": {
                                            "type": "string",
                                            "format": "uuid"
                                        }
                                    }
                                },
                                "type": "object"
                            }
                        }
                    }
                },
                "responses": {
                    "204": {
                        "description": "No Content"
                    },
                    "404": {
                        "description": "One or more ids missing"
                    },
                    "429": {
                        "description": "Rate limited"
                    }
                }
            }
        },
        "/roles": {
            "get": {
                "tags": [
                    "roles"
                ],
                "operationId": "roles.index",
                "parameters": [
                    {
                        "name": "limit",
                        "in": "query",
                        "schema": {
                            "type": "integer",
                            "maximum": 1000,
                            "minimum": 1
                        }
                    },
                    {
                        "name": "offset",
                        "in": "query",
                        "schema": {
                            "type": "integer",
                            "minimum": 0
                        }
                    },
                    {
                        "name": "guard",
                        "in": "query",
                        "schema": {
                            "type": "string"
                        }
                    },
                    {
                        "name": "organization_id",
                        "in": "query",
                        "schema": {
                            "type": "string",
                            "format": "uuid"
                        }
                    },
                    {
                        "name": "is_system",
                        "in": "query",
                        "schema": {
                            "type": "boolean"
                        }
                    },
                    {
                        "name": "level_min",
                        "in": "query",
                        "schema": {
                            "type": "integer",
                            "minimum": 0
                        }
                    },
                    {
                        "name": "level_max",
                        "in": "query",
                        "schema": {
                            "type": "integer",
                            "minimum": 0
                        }
                    },
                    {
                        "name": "has_parent",
                        "in": "query",
                        "schema": {
                            "type": "boolean"
                        }
                    }
                ],
                "responses": {
                    "200": {
                        "description": "OK"
                    },
                    "422": {
                        "description": "Invalid query parameter"
                    }
                }
            },
            "post": {
                "tags": [
                    "roles"
                ],
                "operationId": "roles.store",
                "requestBody": {
                    "required": true,
                    "content": {
                        "application/json": {
                            "schema": {
                                "properties": {
                                    "name": {
                                        "type": "string"
                                    },
                                    "display_name": {
                                        "type": [
                                            "string",
                                            "null"
                                        ]
                                    },
                                    "guard_name": {
                                        "type": "string"
                                    },
                                    "organization_id": {
                                        "type": [
                                            "string",
                                            "null"
                                        ],
                                        "format": "uuid"
                                    },
                                    "level": {
                                        "type": "integer"
                                    },
                                    "is_system": {
                                        "type": "boolean"
                                    },
                                    "parent_role_id": {
                                        "type": [
                                            "string",
                                            "null"
                                        ],
                                        "format": "uuid"
                                    },
                                    "translations": {
                                        "type": "object"
                                    }
                                },
                                "type": "object"
                            }
                        }
                    }
                },
                "responses": {
                    "201": {
                        "description": "Created",
                        "content": {
                            "application/json": {
                                "schema": {
                                    "properties": {
                                        "data": {
                                            "$ref": "#/components/schemas/Role"
                                        }
                                    },
                                    "type": "object"
                                }
                            }
                        }
                    },
                    "422": {
                        "description": "Validation failed"
                    }
                }
            }
        },
        "/roles/{role}/clone": {
            "post": {
                "tags": [
                    "roles"
                ],
                "description": "Subject to the `access-bulk` rate limiter.",
                "operationId": "roles.clone",
                "parameters": [
                    {
                        "name": "role",
                        "in": "path",
                        "required": true,
                        "schema": {
                            "type": "string",
                            "format": "uuid"
                        }
                    }
                ],
                "requestBody": {
                    "required": true,
                    "content": {
                        "application/json": {
                            "schema": {
                                "properties": {
                                    "name": {
                                        "type": "string"
                                    },
                                    "display_name": {
                                        "type": [
                                            "string",
                                            "null"
                                        ]
                                    }
                                },
                                "type": "object"
                            }
                        }
                    }
                },
                "responses": {
                    "201": {
                        "description": "Created"
                    },
                    "404": {
                        "description": "Source role not found"
                    },
                    "422": {
                        "description": "Validation failed"
                    },
                    "429": {
                        "description": "Rate limited"
                    }
                }
            }
        },
        "/roles/{role}/users/bulk": {
            "post": {
                "tags": [
                    "roles"
                ],
                "description": "Subject to the `access-bulk` rate limiter. Idempotent.",
                "operationId": "roles.bulkAssignUsers",
                "parameters": [
                    {
                        "name": "role",
                        "in": "path",
                        "required": true,
                        "schema": {
                            "type": "string",
                            "format": "uuid"
                        }
                    }
                ],
                "requestBody": {
                    "required": true,
                    "content": {
                        "application/json": {
                            "schema": {
                                "properties": {
                                    "user_ids": {
                                        "type": "array",
                                        "items": {
                                            "type": "string",
                                            "format": "uuid"
                                        }
                                    },
                                    "organization_id": {
                                        "type": [
                                            "string",
                                            "null"
                                        ],
                                        "format": "uuid"
                                    }
                                },
                                "type": "object"
                            }
                        }
                    }
                },
                "responses": {
                    "200": {
                        "description": "OK"
                    },
                    "404": {
                        "description": "Role not found"
                    },
                    "429": {
                        "description": "Rate limited"
                    }
                }
            }
        },
        "/audit": {
            "get": {
                "tags": [
                    "audit"
                ],
                "operationId": "audit.index",
                "parameters": [
                    {
                        "name": "event",
                        "in": "query",
                        "schema": {
                            "type": "string"
                        }
                    },
                    {
                        "name": "actor_id",
                        "in": "query",
                        "schema": {
                            "type": "string",
                            "format": "uuid"
                        }
                    },
                    {
                        "name": "tenant_id",
                        "in": "query",
                        "schema": {
                            "type": "string",
                            "format": "uuid"
                        }
                    },
                    {
                        "name": "since",
                        "in": "query",
                        "schema": {
                            "type": "string",
                            "format": "date-time"
                        }
                    },
                    {
                        "name": "until",
                        "in": "query",
                        "schema": {
                            "type": "string",
                            "format": "date-time"
                        }
                    },
                    {
                        "name": "limit",
                        "in": "query",
                        "schema": {
                            "type": "integer"
                        }
                    },
                    {
                        "name": "offset",
                        "in": "query",
                        "schema": {
                            "type": "integer"
                        }
                    }
                ],
                "responses": {
                    "200": {
                        "description": "OK",
                        "content": {
                            "application/json": {
                                "schema": {
                                    "properties": {
                                        "data": {
                                            "type": "array",
                                            "items": {
                                                "$ref": "#/components/schemas/AuditEntry"
                                            }
                                        },
                                        "meta": {
                                            "$ref": "#/components/schemas/PaginatedMeta"
                                        }
                                    },
                                    "type": "object"
                                }
                            }
                        }
                    }
                }
            }
        },
        "/modules/{id}": {
            "get": {
                "tags": [
                    "modules"
                ],
                "operationId": "modules.show",
                "parameters": [
                    {
                        "name": "id",
                        "in": "path",
                        "required": true,
                        "schema": {
                            "type": "string",
                            "format": "uuid"
                        }
                    }
                ],
                "responses": {
                    "200": {
                        "description": "OK",
                        "content": {
                            "application/json": {
                                "schema": {
                                    "properties": {
                                        "data": {
                                            "$ref": "#/components/schemas/Module"
                                        }
                                    },
                                    "type": "object"
                                }
                            }
                        }
                    },
                    "404": {
                        "description": "Not found"
                    }
                }
            },
            "put": {
                "tags": [
                    "modules"
                ],
                "operationId": "modules.update",
                "parameters": [
                    {
                        "name": "id",
                        "in": "path",
                        "required": true,
                        "schema": {
                            "type": "string",
                            "format": "uuid"
                        }
                    }
                ],
                "requestBody": {
                    "required": true,
                    "content": {
                        "application/json": {
                            "schema": {
                                "properties": {
                                    "name": {
                                        "type": "string"
                                    },
                                    "redirect": {
                                        "type": [
                                            "string",
                                            "null"
                                        ]
                                    },
                                    "icon": {
                                        "type": [
                                            "string",
                                            "null"
                                        ]
                                    },
                                    "root_module_id": {
                                        "type": [
                                            "string",
                                            "null"
                                        ],
                                        "format": "uuid"
                                    },
                                    "sort_order": {
                                        "type": "integer"
                                    },
                                    "is_active": {
                                        "type": "boolean"
                                    },
                                    "translations": {
                                        "type": "object"
                                    }
                                },
                                "type": "object"
                            }
                        }
                    }
                },
                "responses": {
                    "200": {
                        "description": "OK",
                        "content": {
                            "application/json": {
                                "schema": {
                                    "properties": {
                                        "data": {
                                            "$ref": "#/components/schemas/Module"
                                        }
                                    },
                                    "type": "object"
                                }
                            }
                        }
                    },
                    "404": {
                        "description": "Not found"
                    },
                    "422": {
                        "description": "Validation failed"
                    }
                }
            },
            "delete": {
                "tags": [
                    "modules"
                ],
                "operationId": "modules.destroy",
                "parameters": [
                    {
                        "name": "id",
                        "in": "path",
                        "required": true,
                        "schema": {
                            "type": "string",
                            "format": "uuid"
                        }
                    }
                ],
                "responses": {
                    "204": {
                        "description": "No Content"
                    },
                    "404": {
                        "description": "Not found"
                    }
                }
            }
        },
        "/roles/{role}": {
            "get": {
                "tags": [
                    "roles"
                ],
                "operationId": "roles.show",
                "parameters": [
                    {
                        "name": "role",
                        "in": "path",
                        "required": true,
                        "schema": {
                            "type": "string",
                            "format": "uuid"
                        }
                    }
                ],
                "responses": {
                    "200": {
                        "description": "OK",
                        "content": {
                            "application/json": {
                                "schema": {
                                    "properties": {
                                        "data": {
                                            "$ref": "#/components/schemas/Role"
                                        }
                                    },
                                    "type": "object"
                                }
                            }
                        }
                    },
                    "404": {
                        "description": "Not found"
                    }
                }
            },
            "put": {
                "tags": [
                    "roles"
                ],
                "operationId": "roles.update",
                "parameters": [
                    {
                        "name": "role",
                        "in": "path",
                        "required": true,
                        "schema": {
                            "type": "string",
                            "format": "uuid"
                        }
                    }
                ],
                "requestBody": {
                    "required": true,
                    "content": {
                        "application/json": {
                            "schema": {
                                "properties": {
                                    "display_name": {
                                        "type": [
                                            "string",
                                            "null"
                                        ]
                                    },
                                    "translations": {
                                        "type": "object"
                                    }
                                },
                                "type": "object"
                            }
                        }
                    }
                },
                "responses": {
                    "200": {
                        "description": "OK",
                        "content": {
                            "application/json": {
                                "schema": {
                                    "properties": {
                                        "data": {
                                            "$ref": "#/components/schemas/Role"
                                        }
                                    },
                                    "type": "object"
                                }
                            }
                        }
                    },
                    "404": {
                        "description": "Not found"
                    },
                    "422": {
                        "description": "Validation failed"
                    }
                }
            },
            "delete": {
                "tags": [
                    "roles"
                ],
                "description": "Soft-delete since v2.8. Restore via POST /roles/{role}/restore.",
                "operationId": "roles.destroy",
                "parameters": [
                    {
                        "name": "role",
                        "in": "path",
                        "required": true,
                        "schema": {
                            "type": "string",
                            "format": "uuid"
                        }
                    }
                ],
                "responses": {
                    "204": {
                        "description": "No Content"
                    },
                    "404": {
                        "description": "Not found"
                    },
                    "422": {
                        "description": "Has bindings or is a system role"
                    }
                }
            }
        },
        "/roles/{role}/restore": {
            "post": {
                "tags": [
                    "roles"
                ],
                "operationId": "roles.restore",
                "parameters": [
                    {
                        "name": "role",
                        "in": "path",
                        "required": true,
                        "schema": {
                            "type": "string",
                            "format": "uuid"
                        }
                    }
                ],
                "responses": {
                    "200": {
                        "description": "OK",
                        "content": {
                            "application/json": {
                                "schema": {
                                    "properties": {
                                        "data": {
                                            "$ref": "#/components/schemas/Role"
                                        }
                                    },
                                    "type": "object"
                                }
                            }
                        }
                    },
                    "404": {
                        "description": "Not found"
                    },
                    "422": {
                        "description": "Role is not soft-deleted"
                    }
                }
            }
        },
        "/roles/{role}/modules": {
            "put": {
                "tags": [
                    "roles"
                ],
                "operationId": "roles.syncModules",
                "parameters": [
                    {
                        "name": "role",
                        "in": "path",
                        "required": true,
                        "schema": {
                            "type": "string",
                            "format": "uuid"
                        }
                    }
                ],
                "requestBody": {
                    "required": true,
                    "content": {
                        "application/json": {
                            "schema": {
                                "properties": {
                                    "modules": {
                                        "type": "array",
                                        "items": {
                                            "properties": {
                                                "module_id": {
                                                    "type": "string",
                                                    "format": "uuid"
                                                },
                                                "is_listing_allowed": {
                                                    "type": "boolean"
                                                },
                                                "is_reading_allowed": {
                                                    "type": "boolean"
                                                },
                                                "is_writing_allowed": {
                                                    "type": "boolean"
                                                },
                                                "is_editing_allowed": {
                                                    "type": "boolean"
                                                },
                                                "is_delete_allowed": {
                                                    "type": "boolean"
                                                }
                                            },
                                            "type": "object"
                                        }
                                    }
                                },
                                "type": "object"
                            }
                        }
                    }
                },
                "responses": {
                    "200": {
                        "description": "OK",
                        "content": {
                            "application/json": {
                                "schema": {
                                    "properties": {
                                        "data": {
                                            "$ref": "#/components/schemas/Role"
                                        }
                                    },
                                    "type": "object"
                                }
                            }
                        }
                    },
                    "404": {
                        "description": "Not found"
                    },
                    "422": {
                        "description": "Validation failed"
                    }
                }
            }
        },
        "/roles/{role}/permission-matrix": {
            "get": {
                "tags": [
                    "roles"
                ],
                "operationId": "roles.permissionMatrix",
                "parameters": [
                    {
                        "name": "role",
                        "in": "path",
                        "required": true,
                        "schema": {
                            "type": "string",
                            "format": "uuid"
                        }
                    }
                ],
                "responses": {
                    "200": {
                        "description": "OK"
                    },
                    "404": {
                        "description": "Not found"
                    }
                }
            }
        },
        "/roles/{role}/bindings/history": {
            "get": {
                "tags": [
                    "roles"
                ],
                "operationId": "roles.bindingsHistory",
                "parameters": [
                    {
                        "name": "role",
                        "in": "path",
                        "required": true,
                        "schema": {
                            "type": "string",
                            "format": "uuid"
                        }
                    },
                    {
                        "name": "limit",
                        "in": "query",
                        "schema": {
                            "type": "integer"
                        }
                    },
                    {
                        "name": "offset",
                        "in": "query",
                        "schema": {
                            "type": "integer"
                        }
                    },
                    {
                        "name": "since",
                        "in": "query",
                        "schema": {
                            "type": "string",
                            "format": "date-time"
                        }
                    },
                    {
                        "name": "module_id",
                        "in": "query",
                        "schema": {
                            "type": "string",
                            "format": "uuid"
                        }
                    }
                ],
                "responses": {
                    "200": {
                        "description": "OK"
                    }
                }
            }
        },
        "/users/{user}/accessible-modules": {
            "get": {
                "tags": [
                    "users"
                ],
                "operationId": "users.accessibleModules",
                "parameters": [
                    {
                        "name": "user",
                        "in": "path",
                        "required": true,
                        "schema": {
                            "type": "string",
                            "format": "uuid"
                        }
                    }
                ],
                "responses": {
                    "200": {
                        "description": "OK"
                    }
                }
            }
        },
        "/languages": {
            "get": {
                "tags": [
                    "languages"
                ],
                "operationId": "languages.index",
                "responses": {
                    "200": {
                        "description": "OK",
                        "content": {
                            "application/json": {
                                "schema": {
                                    "properties": {
                                        "data": {
                                            "type": "array",
                                            "items": {
                                                "$ref": "#/components/schemas/Language"
                                            }
                                        }
                                    },
                                    "type": "object"
                                }
                            }
                        }
                    }
                }
            },
            "post": {
                "tags": [
                    "languages"
                ],
                "operationId": "languages.store",
                "requestBody": {
                    "required": true,
                    "content": {
                        "application/json": {
                            "schema": {
                                "properties": {
                                    "code": {
                                        "type": "string"
                                    },
                                    "name": {
                                        "type": "string"
                                    },
                                    "is_default": {
                                        "type": "boolean"
                                    },
                                    "is_active": {
                                        "type": "boolean"
                                    }
                                },
                                "type": "object"
                            }
                        }
                    }
                },
                "responses": {
                    "201": {
                        "description": "Created",
                        "content": {
                            "application/json": {
                                "schema": {
                                    "properties": {
                                        "data": {
                                            "$ref": "#/components/schemas/Language"
                                        }
                                    },
                                    "type": "object"
                                }
                            }
                        }
                    },
                    "422": {
                        "description": "Validation failed"
                    }
                }
            }
        },
        "/languages/{id}": {
            "get": {
                "tags": [
                    "languages"
                ],
                "operationId": "languages.show",
                "parameters": [
                    {
                        "name": "id",
                        "in": "path",
                        "required": true,
                        "schema": {
                            "type": "string",
                            "format": "uuid"
                        }
                    }
                ],
                "responses": {
                    "200": {
                        "description": "OK",
                        "content": {
                            "application/json": {
                                "schema": {
                                    "properties": {
                                        "data": {
                                            "$ref": "#/components/schemas/Language"
                                        }
                                    },
                                    "type": "object"
                                }
                            }
                        }
                    },
                    "404": {
                        "description": "Not found"
                    }
                }
            },
            "put": {
                "tags": [
                    "languages"
                ],
                "operationId": "languages.update",
                "parameters": [
                    {
                        "name": "id",
                        "in": "path",
                        "required": true,
                        "schema": {
                            "type": "string",
                            "format": "uuid"
                        }
                    }
                ],
                "requestBody": {
                    "required": true,
                    "content": {
                        "application/json": {
                            "schema": {
                                "properties": {
                                    "code": {
                                        "type": "string"
                                    },
                                    "name": {
                                        "type": "string"
                                    },
                                    "is_default": {
                                        "type": "boolean"
                                    },
                                    "is_active": {
                                        "type": "boolean"
                                    }
                                },
                                "type": "object"
                            }
                        }
                    }
                },
                "responses": {
                    "200": {
                        "description": "OK",
                        "content": {
                            "application/json": {
                                "schema": {
                                    "properties": {
                                        "data": {
                                            "$ref": "#/components/schemas/Language"
                                        }
                                    },
                                    "type": "object"
                                }
                            }
                        }
                    },
                    "404": {
                        "description": "Not found"
                    },
                    "422": {
                        "description": "Validation failed"
                    }
                }
            },
            "delete": {
                "tags": [
                    "languages"
                ],
                "operationId": "languages.destroy",
                "parameters": [
                    {
                        "name": "id",
                        "in": "path",
                        "required": true,
                        "schema": {
                            "type": "string",
                            "format": "uuid"
                        }
                    }
                ],
                "responses": {
                    "204": {
                        "description": "No Content"
                    },
                    "404": {
                        "description": "Not found"
                    },
                    "422": {
                        "description": "Default language cannot be deleted"
                    }
                }
            }
        },
        "/languages/{id}/default": {
            "put": {
                "tags": [
                    "languages"
                ],
                "operationId": "languages.setDefault",
                "parameters": [
                    {
                        "name": "id",
                        "in": "path",
                        "required": true,
                        "schema": {
                            "type": "string",
                            "format": "uuid"
                        }
                    }
                ],
                "responses": {
                    "200": {
                        "description": "OK",
                        "content": {
                            "application/json": {
                                "schema": {
                                    "properties": {
                                        "data": {
                                            "$ref": "#/components/schemas/Language"
                                        }
                                    },
                                    "type": "object"
                                }
                            }
                        }
                    },
                    "404": {
                        "description": "Not found"
                    }
                }
            }
        }
    },
    "components": {
        "schemas": {
            "Module": {
                "properties": {
                    "id": {
                        "description": "Central holder for the package's OpenAPI annotations.\n\nAll `#[OA\\*]` attributes for the package's public REST surface live\nhere rather than being spread across the controllers. Rationale:\n\n1. Controllers stay readable — no 200-line attribute prefaces.\n2. `php artisan access:openapi` scans only this one file, which is\nfast and predictable.\n3. A breaking response shape change requires editing exactly one\nplace + bumping `AddApiVersionHeader::API_VERSION`.\n\nThe spec covers the routes that live under\n`config('access.route_prefix')`. Path parameters use UUID format.",
                        "type": "string",
                        "format": "uuid"
                    },
                    "slug": {
                        "type": "string"
                    },
                    "name": {
                        "type": "string"
                    },
                    "icon": {
                        "type": [
                            "string",
                            "null"
                        ]
                    },
                    "redirect": {
                        "type": [
                            "string",
                            "null"
                        ]
                    },
                    "root_module_id": {
                        "type": [
                            "string",
                            "null"
                        ],
                        "format": "uuid"
                    },
                    "sort_order": {
                        "type": "integer"
                    },
                    "is_active": {
                        "type": "boolean"
                    },
                    "translations": {
                        "type": "object"
                    },
                    "created_at": {
                        "type": "string",
                        "format": "date-time"
                    },
                    "updated_at": {
                        "type": "string",
                        "format": "date-time"
                    }
                },
                "type": "object"
            },
            "Role": {
                "properties": {
                    "id": {
                        "type": "string",
                        "format": "uuid"
                    },
                    "name": {
                        "type": "string"
                    },
                    "display_name": {
                        "type": [
                            "string",
                            "null"
                        ]
                    },
                    "guard_name": {
                        "type": "string"
                    },
                    "level": {
                        "type": "integer"
                    },
                    "is_system": {
                        "type": "boolean"
                    },
                    "parent_role_id": {
                        "type": [
                            "string",
                            "null"
                        ],
                        "format": "uuid"
                    },
                    "organization_id": {
                        "type": [
                            "string",
                            "null"
                        ],
                        "format": "uuid"
                    },
                    "translations": {
                        "type": "object"
                    },
                    "modules": {
                        "type": "array",
                        "items": {
                            "type": "object"
                        }
                    },
                    "created_at": {
                        "type": "string",
                        "format": "date-time"
                    },
                    "updated_at": {
                        "type": "string",
                        "format": "date-time"
                    }
                },
                "type": "object"
            },
            "Language": {
                "properties": {
                    "id": {
                        "type": "string",
                        "format": "uuid"
                    },
                    "code": {
                        "type": "string"
                    },
                    "name": {
                        "type": "string"
                    },
                    "is_default": {
                        "type": "boolean"
                    },
                    "is_active": {
                        "type": "boolean"
                    }
                },
                "type": "object"
            },
            "PaginatedMeta": {
                "properties": {
                    "total": {
                        "type": "integer"
                    },
                    "limit": {
                        "type": "integer"
                    },
                    "offset": {
                        "type": "integer"
                    }
                },
                "type": "object"
            },
            "Error": {
                "properties": {
                    "message": {
                        "type": "string"
                    },
                    "error_type": {
                        "type": "string"
                    },
                    "errors": {
                        "type": [
                            "object",
                            "null"
                        ]
                    }
                },
                "type": "object"
            },
            "AuditEntry": {
                "properties": {
                    "id": {
                        "type": "string",
                        "format": "uuid"
                    },
                    "event_name": {
                        "type": "string"
                    },
                    "actor_id": {
                        "type": [
                            "string",
                            "null"
                        ],
                        "format": "uuid"
                    },
                    "tenant_id": {
                        "type": [
                            "string",
                            "null"
                        ],
                        "format": "uuid"
                    },
                    "payload": {
                        "type": "object"
                    },
                    "occurred_at": {
                        "type": "string",
                        "format": "date-time"
                    },
                    "entry_hash": {
                        "description": "sha256 hex of previous_hash || canonical(this). Present only when access.audit.hash_chain.enabled is true.",
                        "type": [
                            "string",
                            "null"
                        ]
                    },
                    "previous_hash": {
                        "type": [
                            "string",
                            "null"
                        ]
                    }
                },
                "type": "object"
            }
        }
    },
    "tags": [
        {
            "name": "modules",
            "description": "Catalog of feature modules."
        },
        {
            "name": "roles",
            "description": "Roles + their permission matrices."
        },
        {
            "name": "languages",
            "description": "Languages + the default-language flag."
        },
        {
            "name": "audit",
            "description": "Audit log query."
        },
        {
            "name": "users",
            "description": "User-facing read endpoints."
        }
    ]
}
